dreamify/__init__.py
dreamify/classicdream.py
dreamify/decorators/__init__.py
dreamify/decorators/optional_global_determinism.py
dreamify/decorators/suppress_logs.py
dreamify/decorators/validators.py
dreamify/deepdream.py
dreamify/dream.py
dreamify/lib/__init__.py
dreamify/lib/configure.py
dreamify/lib/feature_extractor.py
dreamify/lib/legacy/__init__.py
dreamify/lib/legacy/legacy_deepdream.py
dreamify/lib/misc/__init__.py
dreamify/lib/misc/flight.wav
dreamify/lib/misc/image_to_video_converter.py
dreamify/lib/models/__init__.py
dreamify/lib/models/base/__init__.py
dreamify/lib/models/base/base_models.py
dreamify/lib/models/base/constants.py
dreamify/lib/models/base/layer_names.py
dreamify/lib/models/classicdream_model.py
dreamify/lib/models/deepdream_model.py
dreamify/lib/models/dream_model.py
dreamify/lib/models/tiled_gradients.py
dreamify/tests/__init__.py
dreamify/tests/integration/__init__.py
dreamify/tests/integration/test_deepdream.py
dreamify/tests/integration/test_dream.py
dreamify/tests/unit/__init__.py
dreamify/tests/unit/test_utils.py
dreamify/utils/__init__.py
dreamify/utils/common.py
dreamify/utils/compare.py
dreamify/utils/dream_utils/__init__.py
dreamify/utils/dream_utils/utils.py
dreamify-1.1.4.dist-info/LICENSE
dreamify-1.1.4.dist-info/METADATA
dreamify-1.1.4.dist-info/WHEEL
dreamify-1.1.4.dist-info/entry_points.txt
dreamify-1.1.4.dist-info/RECORD
