Metadata-Version: 2.3
Name: dreamify
Version: 1.1.4
Summary: 
Author: kenny
Author-email: 97374837+kankenny@users.noreply.github.com
Requires-Python: >=3.10
Classifier: Programming Language :: Python :: 3
Classifier: Programming Language :: Python :: 3.10
Classifier: Programming Language :: Python :: 3.11
Classifier: Programming Language :: Python :: 3.12
Classifier: Programming Language :: Python :: 3.13
Requires-Dist: imageio (>=2.37.0,<3.0.0)
Requires-Dist: ipython (>=7.34.0,<9.0.0)
Requires-Dist: moviepy (>=2.1.2,<3.0.0)
Requires-Dist: pillow (>=10.0.0,<=11.1.0)
Requires-Dist: psutil (>=7.0.0,<8.0.0)
Requires-Dist: tensorflow (>=2.17.1,<3.0.0)
Requires-Dist: tqdm (>=4.67.1,<5.0.0)
